funcnodes_span/__init__.py
funcnodes_span/_baseline.py
funcnodes_span/_curves.py
funcnodes_span/_smoothing.py
funcnodes_span/baseline.py
funcnodes_span/curves.py
funcnodes_span/fitting.py
funcnodes_span/normalization.py
funcnodes_span/peak_analysis.py
funcnodes_span/peaks.py
funcnodes_span/smoothing.py
funcnodes_span-1.0.1.dist-info/METADATA
funcnodes_span-1.0.1.dist-info/WHEEL
funcnodes_span-1.0.1.dist-info/entry_points.txt
funcnodes_span-1.0.1.dist-info/licenses/LICENSE
funcnodes_span-1.0.1.dist-info/RECORD
